{
    "edits": {
        "total": 4261,
        "accepted": 759,
        "autoEdits": 3483,
        "totalApplied": 4242,
        "votedDown": 2,
        "failed": 2,
        "cancelled": 15,
        "open": 0,
        "last24Hours": 0
    },
    "votes": {
        "yes": 63,
        "no": 0,
        "abstain": 0
    },
    "addedEntities": {
        "artist": 191,
        "coverArt": 650,
        "event": 1,
        "label": 19,
        "recording": 1,
        "release": 451,
        "releaseGroup": 434,
        "series": 4
    },
    "tagsAndRatings": {
        "tagsUpvoted": 195,
        "tagsDownvoted": 3,
        "ratings": 10
    }
}
